<?xml version="1.0" encoding="utf-8"?>
<FormEntry>
  <General>
    <FormName>Normal</FormName>
    <Height>0.3</Height>
    <Weight>0.6</Weight>
    <Male>500</Male>
    <Female>500</Female>
    <BodyStyle />
  </General>
  <BaseStats>
    <HP>40</HP>
    <Atk>27</Atk>
    <Def>60</Def>
    <SpAtk>37</SpAtk>
    <SpDef>50</SpDef>
    <Speed>66</Speed>
  </BaseStats>
  <FormInfo>
    <Type1>Grass</Type1>
    <Type2>Fairy</Type2>
    <Ability1>Prankster</Ability1>
    <Ability2>Infiltrator</Ability2>
    <Ability3>Chlorophyll</Ability3>
    <Exp>56</Exp>
  </FormInfo>
  <Moves>
    <LevelUpMoves>
      <LevelUpMove>
        <Level>0</Level>
        <Name>Absorb</Name>
      </LevelUpMove>
      <LevelUpMove>
        <Level>0</Level>
        <Name>Fairy Wind</Name>
      </LevelUpMove>
      <LevelUpMove>
        <Level>4</Level>
        <Name>Growth</Name>
      </LevelUpMove>
      <LevelUpMove>
        <Level>8</Level>
        <Name>Leech Seed</Name>
      </LevelUpMove>
      <LevelUpMove>
        <Level>10</Level>
        <Name>Stun Spore</Name>
      </LevelUpMove>
      <LevelUpMove>
        <Level>13</Level>
        <Name>Mega Drain</Name>
      </LevelUpMove>
      <LevelUpMove>
        <Level>17</Level>
        <Name>Cotton Spore</Name>
      </LevelUpMove>
      <LevelUpMove>
        <Level>19</Level>
        <Name>Razor Leaf</Name>
      </LevelUpMove>
      <LevelUpMove>
        <Level>22</Level>
        <Name>Poison Powder</Name>
      </LevelUpMove>
      <LevelUpMove>
        <Level>26</Level>
        <Name>Giga Drain</Name>
      </LevelUpMove>
      <LevelUpMove>
        <Level>28</Level>
        <Name>Charm</Name>
      </LevelUpMove>
      <LevelUpMove>
        <Level>31</Level>
        <Name>Helping Hand</Name>
      </LevelUpMove>
      <LevelUpMove>
        <Level>35</Level>
        <Name>Energy Ball</Name>
      </LevelUpMove>
      <LevelUpMove>
        <Level>37</Level>
        <Name>Cotton Guard</Name>
      </LevelUpMove>
      <LevelUpMove>
        <Level>40</Level>
        <Name>Sunny Day</Name>
      </LevelUpMove>
      <LevelUpMove>
        <Level>44</Level>
        <Name>Endeavor</Name>
      </LevelUpMove>
      <LevelUpMove>
        <Level>46</Level>
        <Name>Solar Beam</Name>
      </LevelUpMove>
    </LevelUpMoves>
    <TMMoves>
      <TMMove>
        <Name>Toxic</Name>
      </TMMove>
      <TMMove>
        <Name>Hidden Power</Name>
      </TMMove>
      <TMMove>
        <Name>Sunny Day</Name>
      </TMMove>
      <TMMove>
        <Name>Taunt</Name>
      </TMMove>
      <TMMove>
        <Name>Protect</Name>
      </TMMove>
      <TMMove>
        <Name>Safeguard</Name>
      </TMMove>
      <TMMove>
        <Name>Frustration</Name>
      </TMMove>
      <TMMove>
        <Name>Solar Beam</Name>
      </TMMove>
      <TMMove>
        <Name>Return</Name>
      </TMMove>
      <TMMove>
        <Name>Double Team</Name>
      </TMMove>
      <TMMove>
        <Name>Facade</Name>
      </TMMove>
      <TMMove>
        <Name>Rest</Name>
      </TMMove>
      <TMMove>
        <Name>Attract</Name>
      </TMMove>
      <TMMove>
        <Name>Round</Name>
      </TMMove>
      <TMMove>
        <Name>Energy Ball</Name>
      </TMMove>
      <TMMove>
        <Name>Flash</Name>
      </TMMove>
      <TMMove>
        <Name>Dream Eater</Name>
      </TMMove>
      <TMMove>
        <Name>Grass Knot</Name>
      </TMMove>
      <TMMove>
        <Name>Swagger</Name>
      </TMMove>
      <TMMove>
        <Name>Sleep Talk</Name>
      </TMMove>
      <TMMove>
        <Name>Substitute</Name>
      </TMMove>
      <TMMove>
        <Name>Nature Power</Name>
      </TMMove>
      <TMMove>
        <Name>Dazzling Gleam</Name>
      </TMMove>
      <TMMove>
        <Name>Confide</Name>
      </TMMove>
    </TMMoves>
    <EggMoves>
      <EggMove>
        <Name>Captivate</Name>
      </EggMove>
      <EggMove>
        <Name>Encore</Name>
      </EggMove>
      <EggMove>
        <Name>Switcheroo</Name>
      </EggMove>
      <EggMove>
        <Name>Tickle</Name>
      </EggMove>
      <EggMove>
        <Name>Worry Seed</Name>
      </EggMove>
      <EggMove>
        <Name>Beat Up</Name>
      </EggMove>
      <EggMove>
        <Name>Fake Tears</Name>
      </EggMove>
      <EggMove>
        <Name>Grass Whistle</Name>
      </EggMove>
      <EggMove>
        <Name>Memento</Name>
      </EggMove>
      <EggMove>
        <Name>Natural Gift</Name>
      </EggMove>
    </EggMoves>
    <DWMoves />
    <EventMoves>
      <EventMove>
        <Name>Encore</Name>
      </EventMove>
      <EventMove>
        <Name>Worry Seed</Name>
      </EventMove>
    </EventMoves>
  </Moves>
</FormEntry>