<?xml version="1.0" encoding="utf-8"?>
<FormEntry>
  <General>
    <FormName>Normal</FormName>
    <Height>0.2</Height>
    <Weight>3</Weight>
    <Male>500</Male>
    <Female>500</Female>
    <BodyStyle />
  </General>
  <BaseStats>
    <HP>57</HP>
    <Atk>80</Atk>
    <Def>91</Def>
    <SpAtk>80</SpAtk>
    <SpDef>87</SpDef>
    <Speed>75</Speed>
  </BaseStats>
  <FormInfo>
    <Type1>Steel</Type1>
    <Type2>Fairy</Type2>
    <Ability1>Prankster</Ability1>
    <Ability2>None</Ability2>
    <Ability3>Magician</Ability3>
    <Exp>165</Exp>
  </FormInfo>
  <Moves>
    <LevelUpMoves>
      <LevelUpMove>
        <Level>0</Level>
        <Name>Fairy Lock</Name>
      </LevelUpMove>
      <LevelUpMove>
        <Level>0</Level>
        <Name>Tackle</Name>
      </LevelUpMove>
      <LevelUpMove>
        <Level>5</Level>
        <Name>Fairy Wind</Name>
      </LevelUpMove>
      <LevelUpMove>
        <Level>8</Level>
        <Name>Astonish</Name>
      </LevelUpMove>
      <LevelUpMove>
        <Level>12</Level>
        <Name>Metal Sound</Name>
      </LevelUpMove>
      <LevelUpMove>
        <Level>15</Level>
        <Name>Spikes</Name>
      </LevelUpMove>
      <LevelUpMove>
        <Level>18</Level>
        <Name>Draining Kiss</Name>
      </LevelUpMove>
      <LevelUpMove>
        <Level>23</Level>
        <Name>Crafty Shield</Name>
      </LevelUpMove>
      <LevelUpMove>
        <Level>27</Level>
        <Name>Foul Play</Name>
      </LevelUpMove>
      <LevelUpMove>
        <Level>32</Level>
        <Name>Torment</Name>
      </LevelUpMove>
      <LevelUpMove>
        <Level>34</Level>
        <Name>Mirror Shot</Name>
      </LevelUpMove>
      <LevelUpMove>
        <Level>36</Level>
        <Name>Imprison</Name>
      </LevelUpMove>
      <LevelUpMove>
        <Level>40</Level>
        <Name>Recycle</Name>
      </LevelUpMove>
      <LevelUpMove>
        <Level>43</Level>
        <Name>Play Rough</Name>
      </LevelUpMove>
      <LevelUpMove>
        <Level>44</Level>
        <Name>Magic Room</Name>
      </LevelUpMove>
      <LevelUpMove>
        <Level>50</Level>
        <Name>Heal Block</Name>
      </LevelUpMove>
    </LevelUpMoves>
    <TMMoves>
      <TMMove>
        <Name>Psyshock</Name>
      </TMMove>
      <TMMove>
        <Name>Calm Mind</Name>
      </TMMove>
      <TMMove>
        <Name>Toxic</Name>
      </TMMove>
      <TMMove>
        <Name>Hidden Power</Name>
      </TMMove>
      <TMMove>
        <Name>Sunny Day</Name>
      </TMMove>
      <TMMove>
        <Name>Hyper Beam</Name>
      </TMMove>
      <TMMove>
        <Name>Light Screen</Name>
      </TMMove>
      <TMMove>
        <Name>Protect</Name>
      </TMMove>
      <TMMove>
        <Name>Rain Dance</Name>
      </TMMove>
      <TMMove>
        <Name>Safeguard</Name>
      </TMMove>
      <TMMove>
        <Name>Frustration</Name>
      </TMMove>
      <TMMove>
        <Name>Return</Name>
      </TMMove>
      <TMMove>
        <Name>Psychic</Name>
      </TMMove>
      <TMMove>
        <Name>Double Team</Name>
      </TMMove>
      <TMMove>
        <Name>Reflect</Name>
      </TMMove>
      <TMMove>
        <Name>Torment</Name>
      </TMMove>
      <TMMove>
        <Name>Facade</Name>
      </TMMove>
      <TMMove>
        <Name>Rest</Name>
      </TMMove>
      <TMMove>
        <Name>Attract</Name>
      </TMMove>
      <TMMove>
        <Name>Thief</Name>
      </TMMove>
      <TMMove>
        <Name>Round</Name>
      </TMMove>
      <TMMove>
        <Name>Giga Impact</Name>
      </TMMove>
      <TMMove>
        <Name>Thunder Wave</Name>
      </TMMove>
      <TMMove>
        <Name>Psych Up</Name>
      </TMMove>
      <TMMove>
        <Name>Swagger</Name>
      </TMMove>
      <TMMove>
        <Name>Sleep Talk</Name>
      </TMMove>
      <TMMove>
        <Name>Substitute</Name>
      </TMMove>
      <TMMove>
        <Name>Flash Cannon</Name>
      </TMMove>
      <TMMove>
        <Name>Dazzling Gleam</Name>
      </TMMove>
      <TMMove>
        <Name>Confide</Name>
      </TMMove>
      <TMMove>
        <Name>Cut</Name>
      </TMMove>
    </TMMoves>
    <EggMoves>
      <EggMove>
        <Name>Iron Defense</Name>
      </EggMove>
      <EggMove>
        <Name>Lock-On</Name>
      </EggMove>
      <EggMove>
        <Name>Switcheroo</Name>
      </EggMove>
    </EggMoves>
    <DWMoves />
    <EventMoves />
  </Moves>
</FormEntry>